{
  "overview": "Dr. NTR University of Health Sciences (NTRUHS) is a public university in the city of Vijayawada, Andhra Pradesh.\n\n\n== History ==\nThe university was established as \"University of Health Sciences\" by the Government of Andhra Pradesh and was inaugurated on 9 April by N. T. Rama Rao, the then-Chief Minister of the state.",
  "accreditation": "",
  "coursesAndFees": [],
  "placements": {
    "avgSalary": "",
    "medianSalary": "",
    "highestSalary": "",
    "highestDomestic": "",
    "placementRate": "",
    "totalOffers": "",
    "companiesVisited": "",
    "internationalOffers": "",
    "topRecruiters": []
  },
  "admissions": {
    "examsAccepted": [],
    "admissionProcess": "",
    "importantDates": ""
  },
  "campus": {
    "area": "",
    "facilities": [],
    "specialNote": ""
  },
  "contact": {
    "phone": "",
    "email": "",
    "address": "",
    "admissionsEmail": ""
  },
  "website": "",
  "lastVerified": "2026-05-07",
  "verifiedBy": "Automated Agent"
}